py_zammad_cti-0.0.2.dist-info/licenses/LICENSE
zammad_cti/__init__.py
zammad_cti/__version__.py
zammad_cti/_client.py
zammad_cti/_type_aliases.py
py_zammad_cti-0.0.2.dist-info/METADATA
py_zammad_cti-0.0.2.dist-info/WHEEL
py_zammad_cti-0.0.2.dist-info/top_level.txt
py_zammad_cti-0.0.2.dist-info/RECORD
