Metadata-Version: 2.4
Name: py-zammad-cti
Version: 0.0.2
Summary: Zammad CTI client
Home-page: https://github.com/hmohammad2520-org/py-zammad-cti
Author: hmohammad
Author-email: hmohammad <hmohammad2520@gmail.com>
License: MIT License
Project-URL: Homepage, https://github.com/hmohammad2520-org/py-zammad-cti
Project-URL: BugTracker, https://github.com/hmohammad2520-org/py-zammad-cti
Keywords: python,library,zammad,cti
Classifier: Programming Language :: Python :: 3
Classifier: License :: OSI Approved :: MIT License
Classifier: Operating System :: OS Independent
Requires-Python: >=3.9
License-File: LICENSE
Requires-Dist: requests==2.32.4
Requires-Dist: classmods==1.2.1
Dynamic: author
Dynamic: home-page
Dynamic: license-file
